a_pandas_ex_xml2df/README.MD
a_pandas_ex_xml2df/__init__.py
a_pandas_ex_xml2df/requirements.txt
a_pandas_ex_xml2df/thirdparty.json
a_pandas_ex_xml2df-0.13.dist-info/LICENSE.rst
a_pandas_ex_xml2df-0.13.dist-info/METADATA
a_pandas_ex_xml2df-0.13.dist-info/WHEEL
a_pandas_ex_xml2df-0.13.dist-info/top_level.txt
a_pandas_ex_xml2df-0.13.dist-info/RECORD
